odoo/addons/edi_bank_statement_oca/README.rst
odoo/addons/edi_bank_statement_oca/__init__.py
odoo/addons/edi_bank_statement_oca/__manifest__.py
odoo/addons/edi_bank_statement_oca/i18n/edi_bank_statement_oca.pot
odoo/addons/edi_bank_statement_oca/models/__init__.py
odoo/addons/edi_bank_statement_oca/models/account_bank_statement.py
odoo/addons/edi_bank_statement_oca/static/description/icon.png
odoo/addons/edi_bank_statement_oca/views/account_bank_statement_views.xml
odoo/addons/edi_bank_statement_oca/views/edi_exchange_record_views.xml
odoo13_addon_edi_bank_statement_oca-13.0.1.0.1.dev1.dist-info/METADATA
odoo13_addon_edi_bank_statement_oca-13.0.1.0.1.dev1.dist-info/WHEEL
odoo13_addon_edi_bank_statement_oca-13.0.1.0.1.dev1.dist-info/top_level.txt
odoo13_addon_edi_bank_statement_oca-13.0.1.0.1.dev1.dist-info/RECORD
